clichain/__init__.py
clichain/cli.py
clichain/pipeline.py
clichain-0.1.1.dist-info/METADATA
clichain-0.1.1.dist-info/RECORD
clichain-0.1.1.dist-info/WHEEL
clichain-0.1.1.dist-info/top_level.txt
tests/__init__.py
tests/test_cli.py
tests/test_pep8.py
tests/test_pipeline.py
