Metadata-Version: 2.1
Name: clichain
Version: 0.1.1
Summary: Create a CLI to chain tasks as a pipeline
Home-page: https://github.com/loicpw/clichain
Author: Loïc Peron
Author-email: peronloic.us@gmail.com
License: MIT License
Download-URL: https://github.com/loicpw/clichain.git
Platform: UNKNOWN
Classifier: Development Status :: 3 - Alpha
Classifier: Intended Audience :: Developers
Classifier: License :: OSI Approved :: MIT License
Classifier: Natural Language :: English
Classifier: Programming Language :: Python
Classifier: Programming Language :: Python :: 3.6
Classifier: Programming Language :: Python :: 3.7
Requires-Dist: click
